[{"id":52621,"name":"Ladder","type":10,"category":553,"actions":["Climb-down"],"coordinates":[[2382,37226],[2430,37230],[2494,37290]],"size":[1,1,120],"rotations":[0,0,0],"colors":[4290715,2130612,3174549,6197685,16711422]},{"id":52614,"name":"Ladder","type":10,"category":664,"actions":["Climb-up"],"coordinates":[[2386,37226],[2494,37286]],"size":[1,1,320],"rotations":[0,0],"colors":[4290715,3174549,6197685]},{"id":52594,"name":"Door","type":0,"category":167,"actions":["Open"],"coordinates":[[2418,37234]],"size":[1,1,251],"rotations":[0],"colors":[5921645,6778492,7239558,8158597]},{"id":52458,"name":"Table","type":10,"category":156,"actions":[],"coordinates":[[2420,37222],[2488,37278]],"size":[2,1,96],"rotations":[2,2],"colors":[4812426,5933739,8432588,8037829,4941176]},{"id":24346,"name":"Bed","type":10,"category":0,"actions":[],"coordinates":[[2422,37236]],"size":[1,2,96],"rotations":[2],"colors":[1795482,2582393,6990537,9149864,10073017]},{"id":52431,"name":"Crate","type":10,"category":0,"actions":[],"coordinates":[[2426,37238],[2494,37278]],"size":[1,1,91],"rotations":[0,0],"colors":[4288637,6523808,8034473,7639457,5996692,2579065]},{"id":52425,"name":"Barrel","type":10,"category":0,"actions":[],"coordinates":[[2482,37294]],"size":[1,1,100],"rotations":[0],"colors":[7761518,8288119,9011328,5727096,5134957,4017253]},{"id":17555,"name":"Bed","type":10,"category":0,"actions":[],"coordinates":[[2482,37288]],"size":[1,2,108],"rotations":[3],"colors":[2582393,6780540,2974350,9147541,2972269]}]