[{"id":15897,"name":"Copper Ladder","type":10,"category":0,"actions":[],"coordinates":[[11158,38622]],"size":[1,1,136],"rotations":[0],"colors":[3307680]},{"id":15916,"name":"middle section","type":10,"category":0,"actions":[],"coordinates":[[11170,38638],[11194,38638]],"size":[1,1,134],"rotations":[0,0],"colors":[3307680,3637934,5540258,3174549]},{"id":15920,"name":"middle section","type":10,"category":0,"actions":[],"coordinates":[[11174,38638],[11190,38638]],"size":[1,1,77],"rotations":[0,0],"colors":[5540258]},{"id":15918,"name":"middle section","type":10,"category":0,"actions":[],"coordinates":[[11178,38638],[11186,38638]],"size":[1,1,134],"rotations":[0,0],"colors":[3307680,3637934,5540258,3174549]},{"id":15900,"name":"Copper Ladder","type":10,"category":0,"actions":[],"coordinates":[[11186,38434]],"size":[1,1,136],"rotations":[0],"colors":[3307680]},{"id":15917,"name":"middle section","type":10,"category":0,"actions":[],"coordinates":[[11194,38626]],"size":[1,1,134],"rotations":[0],"colors":[3307680,3637934,5540258,3174549]}]