[{"id":14738,"name":"Tree","type":10,"category":0,"actions":[],"coordinates":[[9222,35806]],"size":[1,1,366],"rotations":[0],"colors":[4934747,65536,4210764,2960701]},{"id":14585,"name":"Bones","type":10,"category":0,"actions":[],"coordinates":[[9268,35792],[9272,35664],[9332,35820],[9352,35700]],"size":[2,2,65],"rotations":[0,0,0,0],"colors":[14474976]},{"id":14576,"name":"Bones","type":10,"category":0,"actions":[],"coordinates":[[9270,35598],[9274,35742],[9358,35758]],"size":[1,1,54],"rotations":[0,0,0],"colors":[14474976]},{"id":14584,"name":"Bones","type":10,"category":0,"actions":[],"coordinates":[[9284,35744],[9408,35772]],"size":[2,2,51],"rotations":[0,0],"colors":[14474976]},{"id":14578,"name":"Bones","type":10,"category":0,"actions":[],"coordinates":[[9306,35734],[9342,35630]],"size":[1,1,44],"rotations":[0,0],"colors":[14474976]},{"id":14583,"name":"Bones","type":10,"category":0,"actions":[],"coordinates":[[9320,35804],[9320,35676]],"size":[2,2,44],"rotations":[0,0],"colors":[14474976]},{"id":14577,"name":"Bones","type":10,"category":0,"actions":[],"coordinates":[[9322,35594],[9402,35738],[9406,35682]],"size":[1,1,25],"rotations":[0,0,0],"colors":[14474976]},{"id":14579,"name":"Bones","type":10,"category":0,"actions":[],"coordinates":[[9366,35642]],"size":[1,1,30],"rotations":[0],"colors":[14474976]}]