[{"id":11192,"name":"Rockslide","type":10,"category":0,"actions":[],"coordinates":[[6992,11204],[6992,11164],[6992,11092],[7036,11216],[7044,11096],[7052,11156],[7052,11048],[7060,11152],[7072,11120],[7072,11084],[7120,11208],[7120,11084],[7124,11132]],"size":[2,2,43],"rotations":[0,0,0,0,0,0,0,0,0,0,0,0,0],"colors":[5540258]},{"id":11193,"name":"Rockslide","type":10,"category":0,"actions":[],"coordinates":[[6996,11104],[7000,11112],[7012,11064],[7028,11184],[7068,11160],[7076,11208],[7088,11108],[7144,11184]],"size":[2,2,43],"rotations":[0,0,0,0,0,0,0,0],"colors":[5540258]},{"id":11191,"name":"Rockslide","type":10,"category":0,"actions":[],"coordinates":[[7060,11160]],"size":[2,2,87],"rotations":[0],"colors":[5540258]},{"id":11185,"name":"Column","type":10,"category":0,"actions":[],"coordinates":[[7104,11096]],"size":[2,2,720],"rotations":[0],"colors":[3307680]},{"id":11184,"name":"Column","type":10,"category":0,"actions":[],"coordinates":[[7112,11168]],"size":[2,2,720],"rotations":[0],"colors":[3307680]}]